{
  "++BwpE": "Error al cargar los datos del servidor: ",
  "++VeJr": "Excepciones de canal",
  "++amr/": "Por favor, pide un nuevo enlace de invitación.",
  "+4YDgS": "Opciones de visualización",
  "+52YnJ": "Aún no hay mensajes",
  "+6YAwo": "seleccionado",
  "+EXB6b": "Comparte este enlace con otros para invitarlos a tu servidor",
  "+HdMsm": "Nombre de la categoría",
  "+IJm1Z": "Silenciado",
  "+K0AvT": "Desconectar",
  "+Kcm/N": "Llamada en curso con {recipientName}",
  "+P5Okg": "Un número",
  "+PHoTK": "Error al editar",
  "+R2E34": "Habilítalas en tu configuración de notificaciones.",
  "+RLc/O": "Copiar enlace de invitación",
  "+V0DW9": "¿Estás seguro de que quieres eliminar este bot del servidor?",
  "+VXlP3": "¡Cuenta creada con éxito! Por favor, inicia sesión.",
  "+aGae9": "Total: {roleMembersTotal}",
  "+dwLjC": "Error al cargar los permisos del canal",
  "+ezGXG": "Visibilidad del servidor",
  "+id0Sp": "Haz clic para añadir la reacción {0}",
  "+odje5": "Eliminar participante",
  "+pwEfQ": "El nombre del servidor no puede estar vacío",
  "+uXsJD": "¡A2F desactivada con éxito!",
  "+uzVIi": "Público (Móvil/SPA)",
  "+vnfjq": "Cambiando el tamaño de la imagen del banner...",
  "+zgZwx": "Esta invitación no es válida o ha expirado.",
  "/3FjXz": "Abrir enlace de invitación",
  "/3ORbg": "Crear uno",
  "/4gGIX": "Copiar al portapapeles",
  "/5q8aT": "Haz clic para revelar",
  "/AOX7T": "Error al unirse a la llamada",
  "/Bh+7r": "Rendimiento",
  "/FE3aV": "Puedes cambiar esto en cualquier momento en la configuración",
  "/Fp6bv": "44.1 kHz (Estándar)",
  "/Hf76T": "Baneando...",
  "/IX/7x": "Otro",
  "/Ok2hq": "Paquetes de idioma de la comunidad",
  "/PzyUK": "Seleccionar servidor",
  "/S8bMP": "Degradado",
  "/TXeTW": "Apagar cámara",
  "/VoM7g": "Recortar avatar",
  "/XQgft": "Descubrir",
  "/XVkxe": "Estás invitado a",
  "/bfjxy": "Quitar ensordecimiento del servidor",
  "/cF7Rs": "Volumen",
  "/duXu5": "en línea",
  "/fwE6J": "Más antiguos",
  "/gQXGv": "Error al actualizar el estado",
  "/mo9tB": "Descripción (Opcional)",
  "/nLvVj": "Ningún miembro coincide con tu búsqueda",
  "/q3weY": "¡Correo electrónico verificado!",
  "/rTz0M": "Audio",
  "/rZmYw": "¡Solicitud de amistad aceptada!",
  "/zrp/i": "Saltar al presente",
  "01N1ZT": "Enlace de invitación generado",
  "01lsQC": "Esperando al participante...",
  "078TDz": "Los usuarios que bloquees aparecerán aquí",
  "07JhQk": "Lista de canales",
  "0A+VM/": "URL de la imagen de fondo",
  "0Cw92o": "Llamada activa",
  "0OuXfX": "No hay amigos en común",
  "0Pk0v5": "Error al enviar el enlace de restablecimiento de contraseña",
  "0RJT5n": "¡Autenticador A2F creado con éxito! Nota: Puede que sea necesario habilitar la aplicación de MFA por separado.",
  "0StR7t": "Introduce tu nueva contraseña",
  "0TMxvF": "Mi Servidor Increíble",
  "0UqCRZ": "Error al cargar las sesiones",
  "0bAN7Q": "Reenviado de",
  "0bLNin": "Las notificaciones están bloqueadas en este dispositivo.",
  "0bbSxn": "Recortar banner",
  "0eSs7V": "Error al desbloquear al usuario",
  "0gS7M5": "Nombre para mostrar",
  "0jddIP": "{0} miembros",
  "0pl5vd": "Enviamos un enlace de verificación a",
  "0sbQbs": "Mensajes directos de miembros del servidor habilitados",
  "0tMugf": "Mencionable",
  "0tXHKp": "El nombre del tema es obligatorio",
  "0wdd7X": "Unirse",
  "0y+X0f": "Por favor, inicia sesión para unirte al canal de voz.",
  "0zMWOY": "Los usuarios deben aceptar los términos antes de ver",
  "10Uy5T": "Subiendo imagen de avatar...",
  "116DXq": "El código de verificación ha expirado. Por favor, intenta iniciar sesión de nuevo.",
  "13+xjB": "URL de Términos de Servicio",
  "16M8sJ": "Reproducir grabación",
  "16uyo+": "Añadir canal",
  "17+pZZ": "Error al eliminar amigo",
  "17aXhN": "Introduce un nombre de usuario para buscar",
  "1CyEtb": "¡Contraseña actualizada con éxito!",
  "1FtQei": "Borrar estado",
  "1IGvCP": "Te damos la bienvenida al chat",
  "1JFLF7": "Selecciona un canal para empezar a chatear",
  "1NLWo5": "Subiendo imagen del banner...",
  "1PS67Y": "Ensordecer en el servidor",
  "1QfxQT": "Descartar",
  "1SHVm4": "Modo lento activo — espera {slowmodeRemaining}s antes de enviar de nuevo",
  "1UzENP": "No",
  "1X7ALB": "Para actualizar tu dirección de correo electrónico, introduce tu contraseña actual por seguridad.",
  "1XQR5u": "Error al buscar usuarios",
  "1d4SuI": "Permisos para {0}",
  "1eBYqn": "¡Correo electrónico verificado! Por favor, inicia sesión.",
  "1h80Kw": "Rol personalizado",
  "1hKEom": "Prioridad",
  "1iY5xv": "Micrófono",
  "1j9aoC": "Tu navegador no soporta la etiqueta de video.",
  "1nfMxB": "Revisa tu correo electrónico",
  "1njn7W": "Claro",
  "1oGOEW": "¿Estás seguro de que quieres eliminar la categoría \"{0}\"? Todos los canales en esta categoría se moverán a sin categorizar.",
  "1pO1zi": "El nombre del servidor es obligatorio",
  "1rBCY8": "Cargando configuración de notificaciones...",
  "1rQmmv": "Personalizar permisos",
  "1sYvcp": "mensaje coincidente",
  "1t/NnN": "Rechazar",
  "1xwBE1": "Cámara encendida",
  "1ztZEr": "Haz clic para ocultar",
  "27cbaF": "Este contenido es de un canal NSFW",
  "28e1Wr": "✗ No se muestra por separado",
  "297Tu0": "Automod",
  "29VNqC": "Error desconocido",
  "29mvhi": "Configuración de Automod guardada",
  "29w7p6": "Subiendo imagen...",
  "2E46g7": "Mostrar por separado en la lista de miembros",
  "2GvilU": "Error al cargar el mensaje",
  "2LD8h0": "Desfijar mensaje",
  "2Moku3": "cambió el icono del canal.",
  "2T3/dQ": "eliminado",
  "2ZAgit": "Ocultar controles automáticamente",
  "2cJCMb": "Autenticación exitosa, pero no se pudo redirigir a OAuth",
  "2eLubN": "Selector de expresiones",
  "2hbnGz": "Configurando...",
  "2lad0+": "Sobre mí",
  "2lcxEO": "Error al autorizar la aplicación",
  "2mAGSj": "Mi Increíble Aplicación",
  "2ogM2T": "Buscar usuarios baneados",
  "2wGPef": "Añade una capa extra de seguridad a tu cuenta",
  "2wZrG0": "Cada enlace de invitación se puede usar múltiples veces",
  "2y9Ojd": "Suelta archivos para adjuntar",
  "2ygf/L": "← Volver",
  "2zaBjr": "Guardar estado",
  "3+uVx3": "Error al reordenar canal: {0}",
  "3/6Rg6": "https://tuapp.com/oauth/callback",
  "31kX5q": "El usuario ya es el propietario del servidor",
  "32GtZe": "Aún no hay amigos",
  "32TndD": "Bloqueado",
  "32YCEH": "Error al buscar usuarios",
  "335PJZ": "Catálogo de traducción (JSON)",
  "34Qhax": "8 horas",
  "36Az/F": "nuevos mensajes",
  "38+WDJ": "Cancelación de eco",
  "38WIzb": "Cerrar búsqueda",
  "3Bcrxs": "• Los bots deben ser invitados a los servidores por administradores",
  "3DDtQA": "Valores predeterminados del servidor (Admin)",
  "3DLYmM": "Error al restablecer la contraseña",
  "3ErQit": "Ir al mensaje",
  "3GRhWr": "Editor de temas",
  "3GhezV": "2 minutos",
  "3NotPv": "Las solicitudes de amistad que recibas aparecerán aquí",
  "3TXCbg": "Servidor ensordecido",
  "3cLOJa": "Crear servidor",
  "3efzOa": "Establece preferencias de notificación diferentes para canales específicos",
  "3oGFTf": "Copia tu clave API de arriba",
  "3oTUp2": "¿Estás seguro de que quieres eliminar \"#{channelName}\"? Esto no se puede deshacer.",
  "3qkggm": "Pantalla completa",
  "3qpwz2": "Las notificaciones están habilitadas en este dispositivo.",
  "3sH6Yk": "Error al salir de la llamada",
  "3u9TwY": "Ocurrió un error al guardar",
  "3y+d4K": "Expulsar miembro",
  "3yfVVv": "Evita que @everyone y @here te notifiquen",
  "479pdJ": "Confirma tu nueva contraseña",
  "47L1V1": "Cerrar imagen",
  "4AUM6J": "Error al enviar el reporte. Por favor, inténtalo de nuevo.",
  "4BITzH": "Error:",
  "4D/eq2": "nuevo mensaje",
  "4DLZUa": "Anular publicación",
  "4DvUAJ": "Estado personalizado",
  "4E+jEv": "Bloqueado — {0}",
  "4EZrJN": "Reglas",
  "4FaOxe": "Error al convertir a cuenta de bot",
  "4FiMi1": "¿Estás seguro de que quieres salir de {0}?",
  "4Fu6cy": "Notificar solo cuando te mencionen",
  "4GLxhy": "Empezando",
  "4HrKtl": "Confirmación de asistencia actualizada a pendiente",
  "4I+mOk": "Editar estado personalizado",
  "4IJmRG": "Quitar silencio al usuario",
  "4LI05Q": "Configuración de categoría",
  "4P1tOP": "Di hola para empezar la conversación",
  "4RVNDE": "Error al cargar los datos del bot",
  "4S6aur": "Redirigiendo en 3 segundos...",
  "4U85fw": "Cliente creado con éxito",
  "4UIhRd": "Introduce el nombre de la categoría...",
  "4VLY42": "Cargando solicitud de autorización...",
  "4XeyTq": "Establece tu nivel de notificación para este servidor",
  "4Yjzqt": "Tipo de servidor",
  "4bl5kp": "Cargando bots del servidor...",
  "4eJbHD": "Crear paquete",
  "4mbrAq": "1 minuto",
  "4wOPAF": "Mensajes guardados",
  "4zXgOb": "El servidor ha deshabilitado @everyone y @here.",
  "53HmwZ": "Selecciona un rol para editar",
  "55s6S3": "Rechazar llamada",
  "5CDZ7q": "Cerrar panel de fijados",
  "5COtUX": "Guardar mensaje",
  "5F6AWL": "soporte@tuapp.com",
  "5GQfEE": "{0} Miembros",
  "5J22Sv": "{oversizedCount} archivo{0} excede el límite de 10MB.",
  "5NAzYL": "Paquete de idioma creado",
  "5TkGXq": "Configuración de privacidad",
  "5UE6Cp": "Desplaza para ver más",
  "5W+bvd": "Notas importantes:",
  "5WAKiF": "Modo lento",
  "5dJK4M": "Roles",
  "5fQCP0": "Llamada en curso de {recipientName}",
  "5hj+Qt": "Introduce los términos que los usuarios deben aceptar...",
  "5k0NLb": "Revisión",
  "5lWFkC": "Iniciar sesión",
  "5mMDoa": "Te han invitado a unirte a un servidor",
  "5nuejR": "Generar nuevo enlace",
  "5qi5+d": "Error al generar el enlace de invitación.",
  "5qogz8": "Configuración del servidor actualizada",
  "5sf2dF": "Aún no hay registros",
  "5vn5Be": "Error al cargar el servidor",
  "6/dCYd": "Visión general",
  "63niL6": "Usuario desconocido",
  "64dQvP": "Tu perfil se actualizó pero hubo un problema al actualizar los detalles de tu cuenta",
  "66S97R": "Por favor, inicia sesión para ver este evento",
  "689pkX": "Detalles de la tarea",
  "6Aih4U": "Desconectado",
  "6FyrFm": "Compartir pantalla",
  "6KN6a6": "Error al eliminar el tema",
  "6LNArx": "Reportante",
  "6LavgR": "Cancelar llamada",
  "6MeTF2": "Permisos del canal",
  "6PXCAo": "Error al desactivar la A2F. Por favor, inténtalo de nuevo.",
  "6SFW1W": "Una aplicación está solicitando acceso a tu cuenta",
  "6V3Ea3": "Copiado",
  "6V6NEa": "Eliminar miembro",
  "6WdDG7": "Página",
  "6YtxFj": "Nombre",
  "6ZQvsG": "CREA UN",
  "6ZYYXc": "{0} Resultados",
  "6exX+8": "Regenerar",
  "6gRgw8": "Reintentar",
  "6h4n3E": "Evita que las menciones de @rol te notifiquen",
  "6hMHni": "Códecs de video: {0}",
  "6m0bcb": "Cargando emojis…",
  "6pQbJO": "Minimizar indicador de llamada",
  "6sDd4a": "Por favor, inicia sesión para unirte a la llamada.",
  "6t6jso": "No tienes permiso para adjuntar archivos",
  "6yQaU8": "Actualizar tarea",
  "6zJnDQ": "Quitar ensordecimiento",
  "72/K9X": "Error al actualizar los valores predeterminados del servidor",
  "73lp8c": "Ver perfil",
  "74cOE4": "No se encontraron nuevos usuarios",
  "7Bj3x9": "Fallido",
  "7CSMoo": "Los canales se listan a la izquierda",
  "7IDDky": "URL de Política de Privacidad",
  "7Jw/XW": "Detalles del error",
  "7MI7VY": "Solicitud de amistad rechazada",
  "7O8dvl": "Conexión:",
  "7Ppwx6": "Error al enviar el mensaje",
  "7PzzBU": "Usuario",
  "7QiL0S": "Compartir pantalla",
  "7RUVCk": "Pendiente — {0}",
  "7TkjAs": "Reproducir video",
  "7UCPhP": "¡Clave API copiada al portapapeles!",
  "7VpPHA": "Confirmar",
  "7ZoQDu": "Acerca de las invitaciones al servidor",
  "7b0fXG": "{0}/oauth2/apps/categories",
  "7d1a0d": "Público",
  "7doZeg": "Generar enlace",
  "7eCTS1": "La A2F está protegiendo tu cuenta actualmente",
  "7eMo+U": "Ir a Inicio",
  "7fIUBE": "ID:",
  "7kb4LU": "Aprobado",
  "7nGhhM": "¿Qué tienes en mente?",
  "7rizPA": "Cuéntanos sobre ti...",
  "7sNhEz": "Nombre de usuario",
  "7vEC4B": "actual",
  "7vKYqp": "(editado)",
  "7vhWI8": "Nueva contraseña",
  "7xMct+": "Configuración de seguridad guardada",
  "7yH8gH": "¿Estás seguro de que quieres eliminar este servidor? Esta acción no se puede deshacer.",
  "80X/M1": "Copiar clave API",
  "812XAU": "Descripción del evento",
  "81d7AR": "Cargando información del evento...",
  "84lAzh": "Aún no hay aplicaciones OAuth2",
  "880xAa": "Protección alta",
  "89g++z": "Abandonar servidor",
  "8DYiyg": "¿Necesitas una cuenta?",
  "8FBPIL": "Introduce un enlace de invitación",
  "8FMTCg": "No tienes permiso para gestionar bots en este servidor",
  "8N/fFo": "Tus marcadores de mensajes personales",
  "8PYAzS": "Convierte tu cuenta de usuario en una cuenta de bot para acceder a la API de Echoed Bot. Esto permitirá que tu cuenta sea invitada a servidores como bot y use funciones específicas de bots.",
  "8Q+lLG": "Chats",
  "8RmQki": "Autorizando...",
  "8TMG9v": "{recipientName} rechazó tu llamada",
  "8VEDbV": "Secreto",
  "8Vns2b": "Icono del servidor",
  "8W5UIU": "Cargando paquetes de idioma...",
  "8Zd0H8": "Roles exentos",
  "8ZsakT": "Contraseña",
  "8fGCNs": "Error al guardar la configuración de notificaciones",
  "8fHllo": "15 segundos",
  "8m0ICt": "Mover a En Progreso",
  "8o3dPc": "Suelta archivos para subir",
  "8odlVW": "Fijar en la parte superior",
  "8p/v6J": "Solo las personas en tu lista de amigos pueden enviarte mensajes directos.",
  "8vETh9": "Mostrar",
  "8wYDMp": "¿Ya tienes una cuenta?",
  "9/Bxh1": "Contenido inapropiado",
  "92o1+U": "Error al eliminar",
  "93Tu17": "Permitir mensajes directos",
  "9I55C4": "NO TE PREOCUPES.",
  "9Jp9y1": "Le pasa a los mejores. Introduce tu correo electrónico y te enviaremos un enlace para restablecer tu contraseña.",
  "9KPPa8": "Error al habilitar la A2F. Por favor, inténtalo de nuevo.",
  "9O2erp": "Puedes intentar el proceso de autorización de nuevo",
  "9Q6NvQ": "(editado hace {days}d)",
  "9UaYQR": "mensajes coincidentes",
  "9Xufh4": "Breve descripción de lo que hace tu bot",
  "9ZvoBu": "Todos los mensajes guardados cargados",
  "9az766": "Llamada entrante",
  "9cDpsw": "Permisos",
  "9g4eX9": "Desfijar mensaje",
  "9kwf8d": "Banear",
  "9mcJ/7": "No se encontraron roles",
  "9o98Gf": "Color de la categoría",
  "9sCgbz": "Se movió {0} a {1}",
  "9x1ekM": "Añadir un Servidor",
  "A/kGYD": "Error al fijar",
  "A06hLB": "Resultados de búsqueda",
  "A0cKFa": "Este es un rol del sistema. No puedes editar sus permisos aquí.",
  "A1taO8": "Buscar",
  "A5i7hf": "Recomendado para la mayoría de los servidores",
  "A9Rhec": "Nombre del canal",
  "AB+Aod": "Avatar subido con éxito",
  "ACjxWW": "Zoom",
  "ADVQ46": "Iniciar sesión",
  "AGZmwV": "Imagen subida con éxito",
  "AJKyHq": "Enviar nuevo correo electrónico de verificación",
  "AJLByM": "10 minutos",
  "AKZN8U": "¡Guardado!",
  "ALZ4SG": "Ensordecer",
  "ANNUr5": "Contestar llamada",
  "AQOR3n": "Bloquear o marcar mensajes que contengan URLs",
  "AQYzXf": "Enviando correo electrónico de verificación...",
  "AU7IRi": "Canal de texto",
  "AURbCJ": "Mensajes fijados",
  "AUXNUB": "Error al resolver el reporte",
  "AXWQrN": "Error al comprobar la disponibilidad",
  "AaDUlx": "Buscar miembros",
  "AbpPzT": "Actualizar aplicación",
  "AgS4eM": "Llamante",
  "Ai2U7L": "Anfitrión",
  "AiGXzD": "Introduce el nombre del canal",
  "AiX0co": "Ignorar (descartar en silencio)",
  "AmI+vx": "Error al guardar la configuración",
  "AnEfbU": "No se encontraron mensajes para",
  "AoxqXM": "Enviar en silencio (sin notificaciones)",
  "Ar4nR/": "Introduce un nombre de usuario",
  "ArN3Xs": "Clave API del bot",
  "AsIULB": "Las solicitudes de amistad que envíes aparecerán aquí",
  "AuZuWh": "Generar un nuevo enlace invalidará el anterior",
  "AuxdBS": "Configuración de privacidad",
  "Ax4+gM": "Aún no has creado ningún paquete de idioma",
  "AxPAXW": "No se encontraron resultados",
  "B2jLcS": "Redirigido desde una aplicación OAuth",
  "BBUDfW": "Urgente",
  "BGIpSK": "Esta invitación ha expirado",
  "BGw+Qc": "Canal de voz",
  "BHsrDx": "Invitaciones",
  "BIDT9R": "Bots",
  "BIxD1T": "Usuarios baneados ({0})",
  "BLglDd": "Cliente actualizado con éxito",
  "BQFRP1": "Mover a Revisión",
  "BRLYXo": "Enlace de restablecimiento de contraseña enviado a tu correo electrónico",
  "BWF1kC": "Buscar mensajes...",
  "BbyMmR": "Por favor, introduce un nombre para tu paquete de idioma",
  "BdNgHC": "Estás baneado de este servidor.",
  "Bdj4LI": "Secreto del cliente",
  "BphJcg": "Error al crear la invitación",
  "Brvd0l": "Reenviar correo electrónico",
  "Bt2yaf": "¡Enlace de invitación copiado al portapapeles!",
  "BttiBS": "Página {logsPage} de {totalLogPages} ({logsTotal} en total)",
  "BwJKBw": "de",
  "BzElbw": "No se encontraron resultados",
  "C3nD/1": "Introduce tu correo electrónico",
  "C4pKXW": "Autenticación de dos factores",
  "C5e3u5": "Emoji, GIFs y Stickers",
  "C6+ZRl": "Alguien",
  "C6OPyh": "Cargando mensajes más antiguos...",
  "C7A6S+": "000000",
  "C8Xbha": "Error al aceptar las reglas. Por favor, inténtalo de nuevo.",
  "CDAdlf": "Eliminar bot",
  "CE+M2e": "Información",
  "CEi+2r": "Canal donde se registran las acciones de automod",
  "CHXUwv": "Conéctate con amigos y empieza a enviar mensajes",
  "CHeXFE": "Estado actualizado",
  "CJkEfx": "Bloquear",
  "CKyk7Q": "Volver",
  "CLKXKV": "Ocurrió un error al aceptar la solicitud",
  "CQpgyQ": "Volver a canales",
  "CSQPC0": "Crear una cuenta",
  "CWsYB3": "Bienvenido de nuevo",
  "Ce8q3L": "Selecciona un canal",
  "CkGQYd": "✓ Mencionable",
  "Cok9c0": "Uniéndose a {0}...",
  "CopI6M": "El miembro ha sido expulsado del servidor",
  "CpGgBW": "Reporte enviado con éxito. Gracias por ayudar a mantener la comunidad segura.",
  "CpKtQl": "¡URL de invitación copiada al portapapeles!",
  "CqgeWd": "Silenciar localmente",
  "CuoNxf": "Uniéndose...",
  "Cz+K13": "15 minutos",
  "CzL7Lg": "Interior",
  "Czbh88": "Todos los idiomas",
  "D+NlUC": "Sistema",
  "D+vXiO": "¿Contraseña?",
  "D0meML": "persona",
  "D2c/D6": "Relevante",
  "D3iCkb": "Fecha de inicio",
  "D3sOo9": "Buscar amigos",
  "D9pxi/": "Salió del servidor",
  "DB8zMK": "Aplicar",
  "DBTW68": "Reporte enviado",
  "DCKkhU": "Contraseña actual",
  "DCRKbe": "Habilitar A2F",
  "DCSTNR": "Llamada inválida",
  "DEGPXe": "Perfil no disponible",
  "DHPu+L": "Ver perfil completo",
  "DHhJ7s": "Anterior",
  "DHnU7i": "Servidor de soporte",
  "DMqzfv": "Este es el comienzo del canal #{0}. Envía un mensaje para iniciar la conversación.",
  "DPfwMq": "Hecho",
  "DU0YtB": "Cargando temas...",
  "DUDhHQ": "Dejar de guardar",
  "DXNvrU": "Descubre bots increíbles para tu alternativa a Discord",
  "DXdaqu": "Tema anulado de publicación",
  "DmJJql": "Haz clic en el enlace para verificar tu cuenta.",
  "Du+zn+": "Buscando...",
  "Dvc8Qg": "Descripción:",
  "Dw1+6+": "¡Ventana emergente bloqueada! Por favor, permite las ventanas emergentes para este sitio e inténtalo de nuevo.",
  "DzmsLV": "Moderación",
  "E/QGRL": "Desactivado",
  "E5eC82": "Selecciona un miembro",
  "E5pHe+": "Revertido a las traducciones integradas",
  "E6L9aZ": "Llamada cancelada a {recipientName}",
  "EBgIRB": "Y LISTO.",
  "ECR7pv": "Debes ser miembro del servidor con acceso de visualización para ver este evento.",
  "EKhpo0": "Ocurrió un error al rechazar la solicitud",
  "EOFF1k": "Creado:",
  "ERVV+r": "Acerca de la configuración de bots",
  "ERZ7Js": "Este enlace de invitación no es válido o ha expirado.",
  "EY4XVW": "Expulsar",
  "EdQY6l": "Ninguno",
  "Ef7StM": "Desconocido",
  "EgRQCt": "Silenciar todas las notificaciones",
  "EhYGkg": "Crea y gestiona tus temas personalizados",
  "Ei1sp3": "{0} te envió una solicitud de amistad",
  "ElR3MZ": "Evento no encontrado",
  "EnqLYU": "Buscar servidores...",
  "EpJ94D": "\"{0}\" se movió a {1}",
  "EsN5ca": "Error al enviar",
  "Ev2r9A": "Sin resultados",
  "EwRxUH": "Códecs de audio: {0}",
  "EyQMHI": "Acoso",
  "Eyi5Ed": "Tu contraseña se ha restablecido con éxito",
  "EzR6wK": "Procesamiento de audio",
  "F/Nk4t": "Servidor silenciado por el administrador",
  "F0Ft6U": "Seleccionar asignado...",
  "F0OKMc": "Editar servidor",
  "F2TtbV": "Elige tu apariencia preferida",
  "F6pfE9": "Activo",
  "F7xbhp": "No tienes permiso para gestionar este canal",
  "F83eo1": "Error al desbanear usuario",
  "FC8qNC": "Eres el propietario de este servidor",
  "FIlVa7": "+ {0} adjunto{1}",
  "FK5/sf": "No se encontraron miembros",
  "FKk3Qp": "Enlace o código de invitación",
  "FNvDMc": "Esta semana",
  "FOPeqj": "Control de ganancia automático",
  "FR3lPz": "Ocurrió un error al eliminar al amigo",
  "FRwKhH": "Ocurrió un error al cancelar la solicitud",
  "FS2tYr": "Publicación de X (Twitter)",
  "FS4b3m": "Toca el botón de menú en la parte superior izquierda para ver los canales.",
  "FTJ37W": "Comprobando disponibilidad...",
  "FTcD5g": "Crea un canal para empezar",
  "FVVJhm": "Advertir",
  "FVyIiV": "Nombre del tema",
  "FYHBjm": "Saltar",
  "FZarZB": "Desbaneando...",
  "FbWKT7": "Arrastra a la carpeta para ocultar",
  "Fc6vja": "Seleccionar miembros",
  "FdTiX8": "Error al cargar la configuración de automod",
  "FiiAwj": "Error al actualizar los permisos del canal",
  "FkhH8q": "Las invitaciones expiran después de 7 días por defecto",
  "FmN5me": "Resolución",
  "FmwES3": "Banear miembro",
  "FsGPqI": "Enviar reporte",
  "Fvt3sT": "Categoría \"{0}\" reordenada",
  "FxVG/l": "Copiado al portapapeles",
  "G+8qH5": "El nombre del canal es obligatorio",
  "G+lkE5": "Estás ensordecido en el servidor por un administrador",
  "G/E5pr": "Mover a Pendientes",
  "G1y8rw": "Crear tema",
  "G5RhpL": "Organizador",
  "G8zWlS": "Error al cargar los mensajes",
  "GB61ZQ": "Llamada entrante...",
  "GCjFWS": "Fijar mensaje",
  "GGH/5s": "Se aplicó el tema \"{0}\"",
  "GJBv49": "Error al abandonar el evento",
  "GLkZHe": "✓ Mostrado por separado",
  "GNcfRk": "Correo de soporte",
  "GS0jut": "No tienes permiso para ver este evento. Debes ser miembro del servidor con acceso de visualización.",
  "GTsg6L": "Has aceptado las reglas. Un administrador debe aprobar tu membresía antes de que puedas acceder a este servidor.",
  "GV2wav": "Error al actualizar el perfil. Por favor, inténtalo de nuevo.",
  "GWYeSZ": "URL base de la API del bot:",
  "Gabn3Y": "Permisos solicitados",
  "Gbmb/s": "Llamada finalizada",
  "GkHG/y": "No se encontraron canales en este servidor",
  "GmU0mK": "Ocultar información del usuario",
  "GnG6Oy": "miembros",
  "GswZF3": "Vista previa:",
  "Gt9msI": "Verificando correo electrónico...",
  "GuUvqW": "Bloquear usuario",
  "GvgSMV": "Copiar enlace del mensaje",
  "GxI9Av": "Notificaciones push",
  "GyHrLt": "Volver a la App",
  "H/LhRS": "Error al actualizar el servidor",
  "H/VXqT": "Solo amigos",
  "H1kWmc": "Introduce el código de verificación de tu aplicación de autenticación",
  "H1tAwA": "Elige tu idioma",
  "H3j6Ro": "Error al actualizar la preferencia de MD",
  "H5wMUb": "+{0} mensajes más",
  "H6RCCZ": "Notificaciones del servidor",
  "H6RSJ3": "Buscando actualizaciones automáticamente...",
  "H7OUPr": "Día",
  "H8Qn1P": "Volver a {serverName}",
  "HFVbC2": "AutoMod",
  "HJetIx": "Este enlace de invitación ha expirado.",
  "HM56Bx": "Creando...",
  "HSXJ84": "¡Correo electrónico actualizado con éxito!",
  "HSmknU": "Buscar miembros del servidor...",
  "HajiZl": "Mes",
  "Hf4qNV": "5 segundos",
  "Hn6rI0": "Miembro desde",
  "Hp1l6f": "Actual",
  "Hr9QI9": "Se movió {0} al canal",
  "HsKjzv": "Sin restricciones",
  "Hw2yNr": "Mi Increíble Bot",
  "Hz2P4i": "Arrastra a la barra lateral para fijar",
  "I/aBNt": "Necesitas permisos de administrador para gestionar los bots del servidor.",
  "I5MfaY": "Cuando los usuarios envíen reportes, aparecerán aquí.",
  "I6/uPI": "Cargando configuración...",
  "I6bw/h": "Banear usuario",
  "I8jr/l": "Introduce tu nueva contraseña a continuación",
  "IDb5ug": "Necesitas permisos de administrador para gestionar automod.",
  "IHYezQ": "Cargando miembros...",
  "IIeRiI": "Eliminar servidor",
  "IJzbZm": "Llamada con {recipientName} {durationText}",
  "IPiZZ3": "Copiar mensaje",
  "IS0nrP": "Crear cuenta",
  "IUwGEM": "Guardar cambios",
  "IdPnI+": "Adjuntos existentes (se conservarán):",
  "Ik0HXZ": "Error al completar el inicio de sesión. Por favor, inténtalo de nuevo.",
  "Ikf7Yz": "¿Estás seguro de que quieres convertir esta cuenta en un bot? Esta acción no se puede deshacer fácilmente.",
  "ImOQa9": "Responder",
  "IoAuJG": "Enviando...",
  "IuLC2D": "Por favor, selecciona un archivo de imagen",
  "IyBivX": "Buscar miembros...",
  "J/PooM": "No hay usuarios bloqueados",
  "J/hVSQ": "{0}",
  "J3Xqm0": "Los usuarios deben esperar {slowModeSeconds}s entre mensajes",
  "JCCO9I": "El tamaño de la imagen debe ser inferior a 2MB",
  "JI0wBf": "Esperando para unirse...",
  "JImd9c": "Editar mensaje",
  "JLwOhh": "Miembros en el rol: {0}",
  "JMQcGz": "Escanear todas las imágenes — bloquear si se detecta NSFW",
  "JOswzR": "Enviado — {0}",
  "JPEqHK": "¡Te has unido a {0}!",
  "JRQLY8": "Solicitud de amistad cancelada",
  "JUVjEj": "Encuentra comunidades a las que unirte",
  "JUwB5j": "Permiso denegado",
  "JWFkfm": "Silenciar servidor",
  "JWgfta": "Cargando mensaje...",
  "JXs/mI": "El mensaje puede estar en el historial más antiguo",
  "JYdw1E": "Invitar personas",
  "JaBzpk": "Error al actualizar los miembros",
  "Jajf+B": "(sin contenido de texto)",
  "JfYSkX": "Asignar roles a los miembros",
  "Jg14Tl": "No se pudo determinar el canal",
  "JheoxW": "¿De qué trata tu servidor?",
  "Ji0Exh": "Por favor, elige un nombre de usuario diferente.",
  "JqwNLg": "No se puede rechazar la llamada: datos de llamada no válidos",
  "JtqFlL": "El servidor está silenciado",
  "Jv8kq1": "Buscar bots...",
  "JvNcuL": "Usar valor predeterminado global",
  "JvPWYg": "Encender cámara",
  "JvUngl": "Fecha y hora",
  "JwpFEC": "Puntos de color",
  "JxhWxU": "en",
  "Jy4h9z": "Nuevo enlace de invitación generado con éxito",
  "Jzl59I": "Tipo de cliente",
  "K/F6pa": "Guardando…",
  "K3WgC9": "No tienes permiso para modificar los permisos del canal",
  "K6pJPW": "Bloquear mensaje",
  "K8h1z9": "Ajustes preestablecidos:",
  "K8hldH": "cambió el nombre del canal:",
  "KH3xzE": "No tienes permiso para adjuntar archivos en este canal.",
  "KM5u4l": "Debes iniciar sesión",
  "KNKCTb": "Pendientes",
  "KNu/VP": "Cambiar banner",
  "KPFIQV": "usuarios",
  "KRkTdf": "Compartir pantalla: {0}",
  "KVeiZe": "Buscar por nombre de usuario o nombre",
  "KWFObn": "Código de autorización",
  "KWUgwY": "Términos y condiciones",
  "KWm8rr": "Nombre del bot",
  "KZXnx4": "Mensajes bloqueados",
  "KbS2K9": "Restablecer contraseña",
  "KgUUVI": "Cargando categorías...",
  "KhtG3o": "Actualizar contraseña",
  "Kjdm7w": "¡Correo de verificación enviado! Revisa tu bandeja de entrada y la carpeta de spam.",
  "KsoVD6": "Secreto de cliente copiado al portapapeles",
  "KwCJks": "Mensaje del sistema",
  "KxRhLs": "Quitar silencio al servidor",
  "L13pb/": "Error al crear la invitación",
  "L1G9/D": "Canal con restricción de edad (NSFW)",
  "L1Rhdt": "Error al subir el archivo. Por favor, inténtalo de nuevo.",
  "L2xsgR": "SÓTANO.",
  "L86zy2": "¡Correo electrónico verificado con éxito!",
  "LIFZxG": "Invitación expirada",
  "LMMGPr": "Enviando...",
  "LMN9WM": "Error al reordenar el canal",
  "LNgO3H": "Invitando...",
  "LOF7vg": "Información del dispositivo",
  "LPim6f": "Error al cargar más entradas",
  "LW4Z2M": "Desbanear",
  "LW9mnL": "Ensordecido",
  "LdmRlX": "Autorizar aplicación",
  "LgD0Cy": "Nombre de la aplicación",
  "LrmrPN": "Expulsando...",
  "LtI9AS": "Propietario",
  "Lvp/TR": "Solo autoriza aplicaciones en las que confíes. Puedes revocar el acceso en cualquier momento en la configuración.",
  "LwP7Yd": "Lista separada por comas de palabras a bloquear",
  "M/rHTh": "Canal no silenciado",
  "M1RnFv": "Expirado",
  "M5dQJw": "Error al generar la clave API",
  "M5mE2U": "Llamando",
  "M8tNIB": "No hay solicitudes enviadas",
  "M90PKG": "Debe tener un correo electrónico verificado",
  "M9l95z": "Actualizar evento",
  "MFKlMB": "Invitar",
  "MHrjPM": "Título",
  "MI+Fvl": "Introduce el nombre del servidor",
  "MImTdx": "No tienes permiso para acceder a este {0}.",
  "MJ73HO": "Error al generar la invitación",
  "MJmU7w": "Selecciona un canal de la barra lateral para empezar a chatear.",
  "MPMIkQ": "Hemos enviado un enlace de restablecimiento de contraseña a",
  "MRB7nI": "Dirección",
  "MXw7Fr": "Nombre del servidor",
  "MZHPuB": "Participantes",
  "MZPWiz": "¿Estás seguro de que quieres expulsar a este miembro?",
  "MjTh/0": "Spoiler",
  "Mou8oo": "Error al abandonar el servidor. Por favor, inténtalo de nuevo.",
  "MtUmPM": "Este canal requiere que aceptes los términos antes de verlo",
  "MyjAbr": "Reenviar",
  "N/v6p6": "Elige un nombre de usuario (mínimo 3 caracteres)",
  "N07TdU": "Error al silenciar el canal",
  "N2GK2b": "Código de autenticador",
  "N40H+G": "Todos",
  "N4qTsL": "El enlace de verificación ha expirado. Por favor, solicita uno nuevo.",
  "N8ByRF": "Introduce tu nombre para mostrar",
  "N8liIj": "Buscar miembros por nombre o correo electrónico...",
  "N9eD5e": "Buscar miembros baneados",
  "NBRdPB": "Amigo",
  "NCIYDF": "Creado por",
  "NFVD1y": "No tienes permiso para crear eventos",
  "NHiAlV": "Creado por:",
  "NHjn8o": "Silenciar temporalmente todas las notificaciones de este servidor",
  "NJWZNe": "Cancelar grabación",
  "NJgqvd": "Requisitos de la contraseña",
  "NKZvr5": "Error al aplicar el tema",
  "NLpnPf": "Error al cargar los miembros del servidor",
  "NOdFZR": "Generando...",
  "NOmjhI": "No se encontraron miembros que coincidan con \"{assigneeSearch}\"",
  "NRXYuy": "Crear aplicación",
  "NUhY+X": "Usa la API de Echoed Bot con tu clave API para interactuar con los servidores",
  "NUrY9o": "Categorías",
  "NWUkDy": "Mostrar calidad de la conexión",
  "NgaR6B": "Introduce tu contraseña",
  "Nh6GTX": "Canal de calendario",
  "NhKvds": "Error al generar el código de invitación.",
  "NjFEpA": "Configura permisos específicos para este {targetType}",
  "NmPNJJ": "Copiar código",
  "Nmi64y": "Debe tener un correo electrónico verificado y una cuenta con más de 5 minutos de antigüedad",
  "NnH3pK": "Prueba",
  "NoNwIX": "Inactivo",
  "NrGxk0": "Error al reordenar la categoría: {0}",
  "Nu4oKW": "Descripción",
  "NuhuBC": "PENDIENTE",
  "Nvu11V": "este usuario",
  "NwiNTb": "miembro",
  "NxgXoy": "Nueva aplicación",
  "NyqPru": "Ahora puedes usar el código de autorización para intercambiarlo por tokens de acceso",
  "Nz4RxO": "Llamada perdida de {recipientName}",
  "O3oNi5": "Correo electrónico",
  "O5hcpv": "Miembro desde",
  "O6H89R": "Resuelto",
  "OAueMY": "Llamando a {0}...",
  "OBsgeT": "{count} personas",
  "ODwSCk": "Enviar un GIF",
  "OHXrDX": "Imagen incrustada",
  "OM1bDW": "Paquete de idioma \"{0}\" aplicado",
  "ONWvwQ": "Subir",
  "ONchxy": "total",
  "OOcVSE": "No se encontraron miembros que coincidan con tu búsqueda",
  "OQDaxZ": "Buscar participantes...",
  "OR475H": "Red",
  "OSBXx5": "Justo ahora",
  "OUrCCh": "Ocurrió un error en la videollamada",
  "OX0KxY": "No tienes permiso para enviar mensajes en este canal.",
  "OYHzN1": "Etiquetas",
  "Oa5K9P": "Servidor público",
  "Ob0S0M": "Gestionar y configurar bots para",
  "OfhWJH": "Restablecer",
  "OfvZzt": "Error al eliminar el administrador del servidor",
  "OgrHqo": "Este es el comienzo de tu historial de mensajes directos con <0>{0}</0>.",
  "On0aF2": "Sitio web",
  "OpgOlq": "Detalles del error (Solo desarrollo)",
  "OqqecQ": "30 segundos",
  "OvBnOM": "Volver a la configuración",
  "OvO76u": "Volver a Iniciar Sesión",
  "P+STWA": "16 kHz (Muy baja)",
  "P1BU0j": "Tasa de fotogramas",
  "P3Dpwt": "Crea tu primera aplicación para empezar con la integración OAuth2",
  "P5GuW3": "Ninguna aplicación coincide con tu búsqueda de",
  "PD88Nh": "Stream de Twitch:",
  "PD9mEt": "Escribe un mensaje...",
  "PDQ5C5": "Las entradas del registro de AutoMod aparecerán aquí cuando se activen las reglas.",
  "PEGxvo": "5 minutos",
  "PJ0BQX": "Llamada con {recipientName}",
  "PJPH6p": "No se encontraron canales",
  "PJUjWq": "Crea tu primer tema personalizado para empezar",
  "PKM6px": "Nada",
  "PLeYjq": "Buscar canales...",
  "PQwBWX": "No se proporcionó ID de llamada.",
  "PRgKWL": "Error al cargar el video",
  "PUqCam": "Creando cuenta...",
  "PUvZUn": "Actualizar perfil",
  "PWhT7a": "Tema sin título",
  "PY2gLF": "Error al subir la imagen del banner",
  "PZ6GT9": "Canal de registro",
  "Pa4yzd": "No se proporcionó el ID del evento",
  "PaQ3df": "Habilitar",
  "PbbQqv": "Ningún bot coincide con tu búsqueda de \"{searchTerm}\"",
  "Pe6QmJ": "Inicio de sesión exitoso pero no se pudo obtener el token de autenticación",
  "Pi1CsG": "Suprimir menciones",
  "PiH3UR": "¡Copiado!",
  "PmZEbt": "Error al subir",
  "Ps6S0h": "Añade un nuevo canal a tu servidor",
  "PsQmAw": "Todos",
  "PshOa7": "Micrófono encendido",
  "Puqqv3": "Error al cancelar la solicitud de amistad",
  "PyumhL": "Por favor, corrige el nombre de usuario antes de guardar",
  "PzzuT0": "Baneado:",
  "Q+X1pn": "¡Solicitud de amistad enviada a <0>{0}</0>!",
  "Q1p5US": "Rechazaste una llamada de {recipientName}",
  "Q2EZzE": "este mensaje",
  "Q2YHlT": "Algoritmos",
  "Q5NVTb": "Página {currentPage} de {0} ({totalClients} en total)",
  "Q6Hd6h": "Privilegios de administrador otorgados con éxito",
  "Q7zdlb": "Quitar silencio al canal",
  "Q9CH45": "Nivel de notificación predeterminado",
  "QDEWii": "Verificado",
  "QETqdL": "¡Has aceptado la invitación al evento!",
  "QHcLEN": "Conectado",
  "QIqjur": "Escanear imágenes de miembros sin rol — desenfocar si se detecta NSFW",
  "QJAPlA": "Error al eliminar el bot",
  "QJQd1J": "Editar perfil",
  "QO5OkQ": "fijó un mensaje en este canal.",
  "QPVenW": "Buscar mensajes",
  "QRF5YW": "Crear tarea",
  "QSYYXg": "que duró {minutes} minuto",
  "QSzGDE": "Ausente",
  "QU21UO": "¡Correo de verificación enviado! Por favor, revisa tu bandeja de entrada.",
  "QUlny5": "¡Te damos la bienvenida a {0}!",
  "Qcqqf3": "El siguiente archivo{0} no es compatible: {rejectedNames}",
  "QfqlE/": "Error al crear el servidor",
  "QgVTJg": "Evita que las menciones de @rol notifiquen a los miembros",
  "Qhb8lT": "Crear nueva aplicación",
  "QiYggx": "Desplaza para más recientes",
  "QoXM4w": "Tema actualizado",
  "Qp1bwZ": "Elige tu tema",
  "QqMq/r": "Archivo demasiado grande",
  "QuNKRX": "Seleccionar cámara",
  "R0owi6": "Color del evento",
  "R40O+V": "Error al rechazar la solicitud de amistad",
  "R7SsBE": "Silenciar",
  "R7YgKs": "Intenta ajustar tus filtros para ver más resultados.",
  "RAMaAx": "Entrante",
  "RG8z6G": "Detalles adicionales (Opcional)",
  "RIcf2t": "Los miembros con estos roles evitarán automod",
  "RK5zqh": "Enviado para revisión",
  "RM+Hni": "Error al actualizar el tema",
  "RPpmyk": "Enlace de verificación inválido. Faltan parámetros obligatorios.",
  "RS2w5v": "Modo silencioso desactivado",
  "RUqTUQ": "Banner subido con éxito",
  "RWw9Lg": "Cerrar modal",
  "RXbEvi": "Actualizando...",
  "RYTEzg": "Página {currentPage} de {0}",
  "RYxrwk": "Texto de los términos",
  "RZP6mL": "¡Bot eliminado del servidor con éxito!",
  "RbHsLQ": "Registro de auditoría actualizado",
  "RfPD/e": "Error al cargar la información del evento",
  "Ri/Rqc": "Invitar al servidor",
  "Rj5wfX": "Convertir a cuenta de bot",
  "RmRZCQ": "Copiar ID de cliente",
  "RoyYUE": "Crear rol",
  "RqOlFF": "Nombre del paquete",
  "RteD+3": " y ",
  "RtiSMg": "Serás redirigido para iniciar sesión en breve.",
  "RuMx0e": "También puedes controlar los permisos de MD por servidor en la configuración de notificaciones de cada servidor.",
  "RutuZn": "Te han invitado a unirte a",
  "RxzN1M": "Habilitado",
  "RypgnJ": "La contraseña se ha restablecido con éxito",
  "RzwXy3": "Activa la moderación automática para este servidor",
  "S0gyyO": "Error al copiar al portapapeles",
  "S1PAf1": "No hay bots en este servidor",
  "S38ttM": "Revisa tu bandeja de entrada y haz clic en el enlace para restablecer tu contraseña",
  "S60KP9": "Configuración del servidor",
  "S6MvaM": "El nombre del servidor no puede exceder los 100 caracteres",
  "S8HFv+": "Volumen del micrófono",
  "SEEyom": "Únete al canal de voz para empezar a hablar",
  "SEcyOF": "\"{0}\" movido dentro de la categoría",
  "SEjYHt": "Reporte {0} exitosamente",
  "SI1cGi": "Tira para actualizar",
  "SIyd1Z": "Introduce tu correo electrónico para recibir un enlace de restablecimiento",
  "SMDbpy": "(editado justo ahora)",
  "SO66ts": "Error al abrir la configuración del bot",
  "SP7KWh": "Flujo de código de autorización OAuth 2.0",
  "SSdi8V": "¡Bot invitado con éxito!",
  "SSs5hQ": "Código de invitación del servidor de soporte",
  "ST+saY": "Ocultar superposición",
  "SYIxS6": "Inicio de sesión requerido",
  "SbnBYl": "Oficial",
  "Se/UIp": "Por hacer",
  "SlfejT": "Error",
  "Sm/5/p": "¡Nuevo correo de verificación enviado! Por favor, revisa tu bandeja de entrada.",
  "SqYyec": "Servidor privado",
  "SrQFQ6": "En voz",
  "SrmuTO": "Esta cuenta está configurada como un bot",
  "Ssvw1b": "Llamando a {recipientName}...",
  "SuT+DW": "Mensaje reenviado",
  "Sxm8rQ": "Usuarios",
  "T+Cbx9": "Añadir reacción",
  "T0MIUY": "¿Eliminar rol?",
  "T3rODb": "No hay entradas en el registro de auditoría",
  "T4fPRn": "Los usuarios baneados se mostrarán aquí",
  "T66NR9": "ACTIVO",
  "T6B2gk": "Error al enviar el mensaje. Por favor, inténtalo de nuevo.",
  "T8OKNX": "Hacer Administrador",
  "T8akS0": "{recipientName} está llamando...",
  "T9imq0": "Reglas de detección",
  "TA3GUC": "Reenviando...",
  "TBhNp5": "Crear un nuevo servidor",
  "TIE7S/": "Eliminar categoría",
  "TKt2IH": "Mostrar contenido",
  "TMLAx2": "Requerido",
  "TMYrdQ": "Mensajes directos",
  "TMuc3s": "{0}/oauth2/authorize",
  "TOWTDS": "Autenticación requerida",
  "TPJ7pt": "Error al cargar las aplicaciones",
  "TatgXM": "Tamaño completo",
  "TbO326": "Aún no hay servidores públicos disponibles",
  "TiKDLH": "Error al mover el canal: {0}",
  "TmcC1z": "Crear nueva contraseña",
  "ToYN0y": "URL del logotipo",
  "TpR7uD": "¡Te damos la bienvenida a #{0}!",
  "TtpxVv": "Error en la verificación del correo electrónico. Por favor, inténtalo de nuevo o contacta a soporte.",
  "Tycaey": "Error al actualizar el nivel de notificación",
  "Tz0i8g": "Ajustes",
  "U011Uh": "Visto por última vez",
  "U2Jb/5": "Enlace de verificación inválido. Por favor, revisa el enlace e inténtalo de nuevo.",
  "U2bq4L": "Comprobando permisos...",
  "U39LfO": "Palabras bloqueadas",
  "U3pytU": "Administrador",
  "U9EkxG": "Los cambios se guardan automáticamente",
  "UBJLuG": "El usuario ha sido desbaneado con éxito",
  "UEV95u": "Múltiples errores detectados. Considera actualizar la página.",
  "UHjHau": "✗ No mencionable",
  "UPt2j/": "Tipo de archivo no compatible",
  "URdr8c": "Actualmente estás en otra llamada. ¿Abandonarla y unirte a este canal?",
  "URmyfc": "Detalles",
  "UY1vmE": "Adjunto",
  "UalxW6": "Contacta al desarrollador de la aplicación para obtener ayuda",
  "UbRKMZ": "Pendiente",
  "Ubg/B+": "Tipo de canal",
  "UeSJde": "0 = desactivado",
  "Ueha8t": "Termina a las {0}",
  "UhEylX": "No tienes permiso para ver este evento.",
  "UhfCzK": "Contacta a soporte si necesitas ayuda con tu cuenta.",
  "UiySxp": "Cerrar lista de miembros",
  "UkM20g": "Revisión pendiente",
  "UlKSMd": "Salió",
  "Um7QPP": "No pudimos encontrar un usuario con ese nombre de usuario o ID.",
  "UmPqCX": "Error en la actualización del correo electrónico: Se requiere la contraseña actual. Por favor, cierra sesión, vuelve a iniciarla e inténtalo de nuevo.",
  "UmtZQJ": "{0} servidores más",
  "UqIV0i": "Evita que @everyone y @here notifiquen a los miembros",
  "UqgUK3": "El servidor ha deshabilitado @everyone.",
  "Ur5nZV": "2 horas",
  "UzWne3": "Enviar mensaje de voz",
  "UzkPxv": "Escanear todas las imágenes — desenfocar si se detecta NSFW",
  "V4sFRu": "Unirse al servidor",
  "V8hC/6": "Inicio de la conversación",
  "V8yTm6": "Borrar búsqueda",
  "VAU5Ow": "Error al cargar los datos del servidor",
  "VEAF6e": "Debe tener al menos 8 caracteres",
  "VEKoJx": "Código de verificación inválido. Por favor, inténtalo de nuevo.",
  "VFv2ZC": "Fecha de finalización",
  "VInoyg": "Nunca recibir notificaciones de este servidor",
  "VJScHU": "Razón",
  "VKsaTi": "Respondiendo a",
  "VLfzHv": "{0}/reset-password",
  "VLhQCW": "Tu evento",
  "VLy2cu": "Página {page} de {totalPages}",
  "VOOFB7": "Aplicar permisos de {presetName}",
  "VOwOgL": "Canal silenciado",
  "VTfZPy": "Acceso denegado",
  "VU2Di6": "Invitación a evento",
  "VZ3ymh": "Sin estado establecido",
  "Va4ypt": "Error al cargar las preferencias de notificación",
  "VaA9mu": "24 horas",
  "VdSWRq": "La aplicación ha sido autorizada con éxito",
  "Vh21HH": "Valor predeterminado del servidor",
  "Vi2Pqx": "por",
  "Vq10dn": "Abandonar llamada",
  "VqnS2e": "No se encontraron usuarios baneados que coincidan con tu búsqueda",
  "Vt/ZBs": "Compartir enlace de invitación",
  "Vw8l6h": "Ocurrió un error",
  "VwEIq5": "Auto baneo",
  "Vwrt0m": "Detección de URL",
  "W0RRjh": "Tablero de tareas",
  "W2y8FY": "Mostrar información del usuario",
  "W2yzzH": " están escribiendo",
  "W3eKjR": "Marcar como por hacer",
  "W7OlPR": "<0>¡Mantén esta clave API segura!</0> Cualquiera con acceso a esta clave puede controlar tu bot. Nunca la compartas públicamente ni la envíes al control de versiones.",
  "W7cXYk": "Ignorar llamada",
  "W7kFlw": "Mensaje reportado",
  "W81Ncj": "Los reportes falsos pueden resultar en acciones contra tu cuenta. Por favor, envía solo reportes genuinos.",
  "W8ekPc": "Volver al panel",
  "WAakm9": "Eliminar canal",
  "WEjXr1": "Este canal está marcado con restricción de edad (NSFW)",
  "WEnfPZ": "Este enlace de invitación ha expirado",
  "WGPS6I": "No se encontraron usuarios que coincidan con \"{0}\"",
  "WHssW9": "Error al añadir administrador al servidor",
  "WJ/f4c": "Volver a Canales",
  "WJ0io3": "Has bloqueado a {0}",
  "WJZl1U": "Usuario desconocido",
  "WLfO1H": "Error al obtener el token de autenticación",
  "WM0jVo": "Iniciar una conversación",
  "WNsmtH": "Establecer estado personalizado",
  "WTx+eB": "Silenciar servidor",
  "WVAl53": "Gestiona los clientes OAuth2 que pueden acceder a Echoed en nombre de los usuarios",
  "WWHy4/": "Contraseña incorrecta. Por favor, inténtalo de nuevo.",
  "WX9USB": "¡Sé el primero en crear uno abajo!",
  "WXDrr0": "Filtros:",
  "WbTDwg": "En progreso",
  "WcZFqz": "Se cerrará tu sesión y serás redirigido al inicio de sesión.",
  "Wf9lru": "Grabar mensaje de voz",
  "WgPJ58": "Error en la actualización del correo electrónico: {0}",
  "WhXbTN": "Conversación eliminada",
  "WsiNoU": "Eliminar bot",
  "WtUYhT": "Se requiere al menos un URI de redireccionamiento",
  "Wxcx4C": "Se limita a 480p @ 15fps",
  "WzMCru": "Perfil de usuario",
  "X1OvJA": "8+ caracteres",
  "X4X8Zv": "No se puede reenviar al mismo canal",
  "X5OGSv": "Error al actualizar el perfil del bot",
  "X7rt25": "¡Cuenta convertida a bot con éxito!",
  "XC9kPj": "Cerrar sesión en todos los dispositivos",
  "XCNV6+": "6 horas",
  "XNrz53": "Cambiando el tamaño de la imagen de avatar...",
  "XOTu2s": "Las tasas de muestreo más altas usan más ancho de banda",
  "XOxZT4": "Iniciando sesión...",
  "XRRafG": "Error al actualizar el estado de administrador",
  "XRZvOH": "Frecuencia de muestreo",
  "XSvKD8": "Pega un objeto JSON con pares clave-valor de traducción. Máx 2MB.",
  "XTdqDN": "Buscar amigos o mensajes",
  "XYcw7G": "URL del sitio web",
  "XYygkg": "Solicitud enviada",
  "XZusCy": "No se pudo cargar el mensaje",
  "Xc95W2": "Debe tener un correo electrónico verificado, una cuenta de más de 5 minutos y ser miembro por más de 10 minutos",
  "XdNgcC": "Listar esta app en el directorio de aplicaciones públicas (los usuarios pueden descubrirla e instalarla)",
  "XeCC/D": "Visto por última vez: {0}",
  "XiaVj+": "Autenticación requerida",
  "XicmhT": "Fecha de vencimiento",
  "XletzW": "Crear categoría",
  "XnE0qP": "Aún no hay canales",
  "XtARSK": "RECHAZADO",
  "Xuef+b": "Reproduciendo...",
  "Xv8FKZ": "¿Estás seguro de que quieres eliminar el rol \"{0}\"? Esta acción no se puede deshacer.",
  "XvjC4F": "Guardando...",
  "XyayEy": "¡Te has unido al servidor!",
  "Y/Jq6D": "Escribe al menos 2 caracteres",
  "Y3SBaw": "Aceptar invitación",
  "YBepty": "Código de invitación inválido",
  "YEZrXF": "Ir a Iniciar Sesión",
  "YIlNII": "Haz clic en este enlace para unirte a mi servidor en Echoed",
  "YJ/lT0": "Cámara: Máx {0}x{1} @ {2}fps",
  "YJ3NDf": "Solo los propietarios y administradores del servidor pueden crear enlaces de invitación",
  "YJafX4": "Enviamos un enlace de restablecimiento de contraseña a tu correo electrónico",
  "YKhNij": "Añadir Bot",
  "YMi3TS": "Elige dónde enviar",
  "YOowcq": "Fecha de vencimiento",
  "YQGs/3": "Introduce el código de 6 dígitos de tu aplicación de autenticación",
  "YQvkSS": "No se encontraron paquetes de idioma de la comunidad",
  "YRwdh4": "Dejar de compartir",
  "YUCdDz": "Autorizar App",
  "YURQaF": "Ver perfil",
  "YUmUm4": "Reporte de {reportType}",
  "YW0B1I": "Notificaciones del sistema",
  "YWB39j": "Configuración de reglas guardada",
  "YXSmtZ": "Descubrimiento de aplicaciones",
  "YZXTrP": "Opcional: Proporciona una URL al panel de configuración de tu bot. Esto se mostrará como un enlace \"Configurar\" en la gestión de bots del servidor.",
  "YZxXK8": "Cerrar selector de emojis",
  "YbPYbp": "Error al unirse al servidor",
  "YcXPo0": "Unirse al canal",
  "YeZn0i": "Error al cargar el registro de auditoría",
  "Yrrg+y": "Objetivo",
  "Yz3cM0": "Invitación al servidor",
  "Z1ykYD": "Error al enviar. Por favor, inténtalo de nuevo.",
  "Z3FXyt": "Cargando...",
  "Z3wpqX": "El tamaño total del archivo excede el límite de 20MB",
  "Z5jmMj": "Silenciar usuario localmente",
  "ZC6q0a": "Mostrar nombres de participantes",
  "ZDTwgq": "CÍRCULO.",
  "ZIJkrY": "Error al guardar la configuración de seguridad",
  "ZLGEhO": "RTT: {0}ms",
  "ZM7Gjp": "Nuevo tema",
  "ZQnN/t": "Guarda los mensajes para tenerlos aquí para una referencia fácil más tarde.",
  "ZROTa2": "Aún no se ha generado ninguna clave API",
  "ZSfKZ/": "Reintentando...",
  "ZV6mcB": "Intenta con palabras clave diferentes o menos específicas.",
  "ZW2hTv": "Miembros del servidor ({0})",
  "ZaJJ+P": "Este proceso normalmente toma poco tiempo. Buscaremos actualizaciones automáticamente.",
  "Zm6uwM": "Únete a la comunidad de Echoed",
  "ZzNhMq": "(editado hace {hrs}h)",
  "a4N/Bg": "Cargar más",
  "a647nU": "Servidor no encontrado",
  "aLf6fH": "¡Autorización exitosa! Ahora puedes cerrar esta ventana.",
  "aP/w80": "Cargando configuración de privacidad...",
  "aPhg1J": "Llamada de {recipientName} {durationText}",
  "aQasny": "Quién puede enviarte mensajes directos",
  "aRI3Om": "Cerrar ventana",
  "aS3rxs": "Solo las personas que comparten un servidor contigo (y tienen los MD habilitados para ese servidor) o que son tus amigos pueden enviarte mensajes.",
  "aW8zuk": "Ocurrió un error al actualizar el servidor",
  "aYmyrv": "URL del panel",
  "aZczPx": "Cargando conversaciones...",
  "aa2Mdy": "Has rechazado la invitación al evento",
  "agPptk": "Medio",
  "ajnMjE": "Error al expulsar al miembro",
  "am0WnA": "Habilitar AutoMod",
  "at1WI0": "Quitar silencio al servidor",
  "az8lvo": "Desactivado",
  "b+E0XF": "No hay servidores en común",
  "b2vAoQ": "Sin categorizar",
  "b7NUY6": "No tienes permiso para crear tareas",
  "b88nLT": "Por favor, revisa y acepta las reglas del servidor para continuar",
  "b9Y4up": "ID de cliente",
  "b9dccI": "Error al guardar la configuración de reglas",
  "bA5h0J": "Error al crear la categoría: {0}",
  "bDjOJd": "Tu correo electrónico ha sido verificado. Redirigiendo a inicio de sesión...",
  "bFtlN/": "Contacta a un administrador del servidor si crees que esto es un error.",
  "bHYIks": "Cerrar sesión",
  "bI4zZt": "Se denegó el permiso de notificación.",
  "bOBdGC": "Modo silencioso activado — sin notificaciones",
  "bQa+H0": "30 minutos",
  "bQksdZ": "Cargar más tareas",
  "bW82k9": "Error al reordenar la categoría",
  "bhKgbl": "Cuéntanos sobre tu servidor...",
  "bhU6f9": "Error al generar el enlace de invitación",
  "bmOZPI": "Copiar secreto del cliente",
  "bmhVEF": "Alternar mensajes fijados",
  "buQo2c": "Ningún usuario ha sido baneado de este servidor",
  "bwRYCn": "Silenciar canal",
  "bwRvnp": "Acción",
  "byKna+": "Ocurrió un error inesperado. Por favor, inténtalo de nuevo.",
  "c3b0B0": "Empezar",
  "c6+TwC": "Cargando roles...",
  "cCZu9v": "No, gracias",
  "cDCpKv": "Acepto",
  "cFCKYZ": "Denegar",
  "cKAgR1": "Error al enviar",
  "cQPKZt": "Ir al panel",
  "cSE9Hk": "Tus datos",
  "cT8oGn": "Tema creado",
  "cTI8zg": "Buscar aplicaciones...",
  "cYTAfv": "ÚNETE AL",
  "cZjIcq": "Aún no hay temas",
  "cevQ4j": "Autenticando usuario...",
  "chRwq/": "Se requiere contraseña",
  "ck+WpO": "Buscar temas de la comunidad...",
  "ckndWD": "Revisa la documentación del bot para ver los endpoints y ejemplos disponibles",
  "ckqVNw": "Los bots pueden ser invitados a tu servidor y configurados con ajustes personalizados.",
  "cn2pBM": "Haz clic para revelar el spoiler",
  "cnGeoo": "Eliminar",
  "ct8XPQ": "El usuario ha sido baneado del servidor",
  "cv/P0F": "Error al bloquear al usuario",
  "cvHryk": "Mostrar {hiddenMemberCount} miembros más",
  "cxw96W": "Busca usuarios introduciendo su nombre o nombre de usuario.",
  "d/CDBx": "Datos de usuario no disponibles",
  "d7LYza": "Error al actualizar la confirmación de asistencia",
  "d7Sa51": "Cambiando el tamaño de la imagen...",
  "d9Ly2g": ", y ",
  "d9bAdc": "Código de autenticador inválido. Por favor, inténtalo de nuevo.",
  "dAZObA": "URIs de redireccionamiento",
  "dCKzkm": "Guardado {0}",
  "dDbD5x": "Términos del canal",
  "dEgA5A": "Cancelar",
  "dGqEP+": "Usuario no encontrado",
  "dRDE6t": "Volver al panel",
  "dSFJgp": "No se encontraron usuarios que coincidan con \"{searchTerm}\"",
  "dSX1LO": "Pega un enlace o código de invitación para unirte a un servidor existente",
  "dUCJry": "Más recientes",
  "dYZvRe": "Esto eliminará a <0>{0}</0> del servidor y evitará que vuelva a unirse.",
  "dZtxqk": "No se pudo encontrar la ubicación de la llamada",
  "daF4YU": "Enlace de restablecimiento inválido. Por favor, solicita uno nuevo.",
  "dbeQoQ": "Video de Vimeo",
  "deuRb8": "Escanea con tu aplicación de autenticación",
  "dj1VCu": "720p (Predeterminado)",
  "dj79uI": "Banear a {0}",
  "dum6Mb": "Actualizando...",
  "dy/AsQ": "Eliminar mensaje (Admin)",
  "e/cvV1": "Verificando...",
  "e02OCO": "Solo puedes buscar por nombre de usuario",
  "e2OrEP": "Explica qué hará tu aplicación con los permisos solicitados",
  "e5wMU/": "Añadido {0}",
  "e8Ed00": "que duró {minutes} minutos",
  "e9FRL2": "Invitación inválida",
  "eE0JZ4": "Versión",
  "eFClyS": "Error al iniciar sesión. Por favor, comprueba tus credenciales.",
  "eIsN5d": "No tienes permiso para gestionar automod en este servidor",
  "eK1P8k": "👑 Propietario del servidor",
  "eLWUJk": "No hay aplicaciones disponibles actualmente",
  "eM45tg": "Eliminar del rol",
  "eP0YFS": "Aceptar llamada",
  "ePK91l": "Editar",
  "eQknlD": "22 kHz (Baja)",
  "eWrFNQ": "El nombre de usuario debe tener al menos 3 caracteres",
  "ea1ykk": "Error al cerrar sesión en todos los dispositivos",
  "ebt0ff": "Introduce el nombre de un servidor",
  "ecUA8p": "Hoy",
  "edWbV6": "Enlace copiado",
  "edZkJt": "Invisible",
  "efUHvr": "Invitar a usuarios",
  "ehZlHt": "Debes aceptar para seguir viendo este canal.",
  "ekCRTP": "Rechazado",
  "ekfzWq": "Ajustes de usuario",
  "em1+IN": "Desbanear usuario",
  "eneWvv": "Borrador",
  "ewjtfx": "Amigo eliminado",
  "eySt5c": "tu.email@ejemplo.com",
  "f2SJ+J": "Servidor grande ({memberCount} miembros) — predeterminado a solo @menciones",
  "f43Mn/": "Descubrir servidores",
  "fBaTZi": "1 (opaco)",
  "fGPtAj": "Sin escaneo",
  "fIqUpB": "Inicia sesión para continuar a Echoed",
  "fJeGyu": "Por favor, introduce un nombre de categoría",
  "fNEu19": "Aprobación pendiente",
  "fR9laE": "Introduce tu contraseña actual",
  "fRjIQM": "Servidores en común",
  "fRoXND": "0 (transparente)",
  "fTGRBE": "No se puede aceptar la llamada: datos de llamada no válidos",
  "fTVZjt": "Asignado a:",
  "fVja9T": "Perfil de usuario",
  "fZg9/7": "Recibir notificaciones push en este dispositivo",
  "fauiYW": "Modo de bajo ancho de banda",
  "fk66/l": "Tu cuenta ha sido deshabilitada debido a actividad sospechosa. Si crees que esto es un error, por favor contacta a soporte.",
  "fk9PYX": "Estás reportando a <0>{targetLabel}</0>",
  "fkRjuY": "La solicitud de autorización no se completó",
  "flmDTf": "Sin descripción",
  "fm/ap6": "Cargando información del servidor...",
  "foSz5f": "Has abandonado la llamada en <0>{0}</0>",
  "ftCVB9": "Error al silenciar el servidor",
  "fufFVs": "Rechazar llamada",
  "fuu/yG": "No se encontraron bots",
  "g3UF2V": "Aceptar",
  "g7jwTg": "Mostrando",
  "g8SUX8": "El nombre del servidor debe tener al menos 1 carácter",
  "g8u20u": "Invitaciones al servidor",
  "g9l6fh": "Marcar como hecho",
  "gAOjAD": "Canal de tareas",
  "gDATVn": "No tienes permiso para añadir reacciones",
  "gITZa8": "Miembros del servidor",
  "gJkKkT": "Error al generar el enlace de invitación.",
  "gLmi0i": "Buscar en esta conversación",
  "gMKLIG": "rol personalizado",
  "gPRsPw": "personas",
  "gX7SWT": "Llamada rechazada",
  "gZ3F9K": "{0} en línea",
  "gjpdaf": "Reportar",
  "glqO38": "APROBADO",
  "glx6on": "¿Olvidaste tu contraseña?",
  "gmFbfT": "Fijar a la barra lateral",
  "gp6A8z": "Autorización fallida",
  "gtXR9E": "Error al aceptar la solicitud de amistad",
  "h41B85": "Error al cargar los miembros baneados",
  "h5bbpz": "Redirigir a:",
  "h69WC6": "Enviado",
  "h6YWOr": "Lista de miembros",
  "h7+4yF": "Por favor, selecciona una razón",
  "h7peZQ": "Permitir",
  "hAPFkB": "Mover a Atrasado",
  "hDHiaT": "Completa tu inicio de sesión seguro",
  "hDaBO3": "No puedes ver el perfil de este usuario.",
  "hENVg4": "votos",
  "hFwWnI": "Configuración de notificaciones",
  "hG89Ed": "Imagen",
  "hH+up8": "Dejar de guardar el mensaje",
  "hIDHNe": "Detectar mensajes repetidos e inundación de mensajes",
  "hImpUW": "Debes iniciar sesión para actualizar tu perfil",
  "hK0Y0J": "Servidor ensordecido por administrador",
  "hPRgrn": "No hay bots disponibles actualmente",
  "hQRttt": "Enviar",
  "hRVcwN": "No hay tareas en esta columna",
  "hWqG3F": "Por determinar",
  "hWxJbb": "Error al crear el tema",
  "hXBe8+": "Aún no hay participantes",
  "hXzOVo": "Siguiente",
  "hYgDIe": "Crear",
  "he3ygx": "Copiar",
  "hgM1nJ": "Seleccionar micrófono",
  "hj370o": "ENLACE DE INVITACIÓN",
  "hkHUZl": "Error al invitar al bot",
  "hlCfY1": "Lo sentimos, pero ocurrió algo inesperado. Por favor, intenta recargar la página.",
  "hlUzav": "Aún no hay mensajes guardados",
  "hp11VA": "Configuración de notificaciones actualizada con éxito",
  "hs1Ex5": "Buscar amigos y mensajes...",
  "htTcVX": "Estado:",
  "i0qMbr": "Inicio",
  "iAL9tI": "Configurar",
  "iBIYJ4": "Enlace de invitación copiado al portapapeles",
  "iDNBZe": "Notificaciones",
  "iFeLoB": "Color sólido",
  "iH8pgl": "Atrás",
  "iHlcZh": "No se encontraron temas",
  "iIuyI8": "• Recibirás una clave API para autenticar tu bot",
  "iK62BN": "Crear categoría (Requiere configuración)",
  "iKOpAz": "JSON no válido. Por favor, pega un objeto JSON válido.",
  "iSAC3k": "Verificar y habilitar",
  "iSfzXo": "Nombre del rol",
  "iVm46+": "Copiar código",
  "iWm9P6": "URL del panel (Opcional)",
  "ibmaFy": "Por favor, introduce tu código de autenticador",
  "ijCZZE": "del grupo.",
  "ilRCh1": "Registro de auditoría",
  "iluPDi": "Seleccionar altavoces",
  "in3Mah": "Bearer {jwt}",
  "ipKBSG": "Buscar en este canal",
  "iqLN+e": "480p (Baja)",
  "ira7oM": "se unió al servidor.",
  "isRobC": "Nuevo",
  "ixTVoh": "Micrófono",
  "ixkTse": "Bot",
  "iyaSUl": "Error al cargar el perfil de usuario.",
  "iypOva": "Volumen del micrófono: {micVolume}%",
  "j2Cfp/": "Pide a un administrador del servidor que invite a tu bot usando el panel de gestión de bots del servidor",
  "j4Q8su": "roles personalizados",
  "j5KznP": "Por favor, espera mientras verificamos tu dirección de correo electrónico.",
  "j9F2UW": "Usuario desbloqueado",
  "jA+Y5R": "inició una llamada.",
  "jAW2nH": "Actualizar roles",
  "jCADOm": "Requerir aceptación de los términos",
  "jEekBe": "¿Abandonar llamada actual?",
  "jFggGL": "Error al subir la imagen",
  "jGrTH0": "No autenticado",
  "jI/uWj": "Actualizar la configuración del canal",
  "jK4feS": "Los secretos del cliente se muestran solo una vez al crearlos. Guárdalos de forma segura y nunca los expongas en el código del lado del cliente. Usa el tipo de cliente \"confidencial\" para aplicaciones del lado del servidor y \"público\" para aplicaciones móviles/SPA.",
  "jKoZME": "Intenta un término de búsqueda diferente",
  "jO6Wol": "Bajada: {0} Mbps",
  "jXdjqv": "Error al crear el paquete de idioma",
  "jYJ5mi": "¡A2F habilitada y aplicada con éxito! Necesitarás tu aplicación de autenticación para futuros inicios de sesión.",
  "jZlrte": "Color",
  "jbq7j2": "Rechazar",
  "jhim3F": "Cargando tablero de tareas...",
  "jj4TRg": "ej. Español (América Latina)",
  "jpGrjI": "Servidor sin silencio",
  "jpRnOs": "Gestión de canales",
  "jpwyWy": "Error al actualizar el registro de auditoría",
  "jqzUyM": "No disponible",
  "jr7mcd": "Se unió a la llamada",
  "jrphPg": "Añadir tarea",
  "jtFB2M": "Gestión de bots",
  "jwXtUS": "Área de chat",
  "jxxbqF": "Buscar roles...",
  "k+i6fQ": "El tamaño de la imagen del banner debe ser inferior a 5MB",
  "k/BTpl": "Buscar mensajes",
  "k1bLf+": "Color de fondo",
  "k1opY7": "Supresión de ruido",
  "k4b5/X": "editado",
  "k6198/": "Tu dirección de correo electrónico ha sido verificada con éxito. Serás redirigido a la configuración en breve.",
  "k62KZc": "Eres un miembro",
  "k99j0U": "Cancelar subida",
  "kACGSQ": "EL",
  "kCn6wb": "Restableciendo...",
  "kDrMSv": "Tu nombre para mostrar",
  "kELalW": "Proporciona más contexto sobre este reporte...",
  "kEmwcX": "{totalCount} {0} guardados",
  "kFkoP6": "PÚBLICO",
  "kI9IVI": "Error al actualizar el nivel de notificación del canal",
  "kIwT5P": "Editar aplicación",
  "kJ8xxs": "Cargar más participantes...",
  "kOvfrl": "Conexión: {0}",
  "kTkmQP": "Error al alternar el estado de publicación",
  "kUlL8W": "Perfil actualizado con éxito",
  "kVtbkN": "Volver a unirse a la llamada",
  "kWJmRL": "Tú",
  "kbXiU8": "Contacta a los administradores del servidor si crees que es un error.",
  "kd3dyR": "Restablecer a valores predeterminados",
  "kdh3Fk": "añadido",
  "ke+JeV": "Error al cargar miembros",
  "keWowJ": "No tienes permiso para enviar mensajes",
  "kiBb99": "Reportar usuario",
  "klpeeZ": "Mi Tema Personalizado",
  "kqU0CW": "Añadir otro URI de redireccionamiento",
  "krhUp8": "Solo registrar",
  "krwTJM": "Sitio web del desarrollador",
  "ksMNJX": "Haz clic para ir al canal de voz",
  "kwS2vD": "Editando mensaje",
  "l+GxCv": "Cargando canales...",
  "l1Do3e": "Añade un bot para ampliar la funcionalidad de tu servidor",
  "l5rije": "Esta ventana se cerrará automáticamente en unos segundos",
  "l8z57Z": "Reenviar mensaje",
  "lCF0wC": "Actualizar",
  "lDjxmT": "Error al enviar",
  "lIooFa": "Callback no válido: falta el código de autorización o la información de error",
  "lMLt6z": "Ocurrió un error al generar el enlace de invitación",
  "lMdXuD": "Tipo:",
  "lRd5+G": "Menciones deshabilitadas",
  "lSrBll": "Navega e invita bots para mejorar tu servidor",
  "lVM/Zv": "{totalReports} reporte{0}",
  "lYWFBr": "Breve descripción de tu aplicación",
  "lYyJvy": "Editar: {0}",
  "lcNkgz": "Selecciona un rol o usuario para configurar los permisos",
  "ld08OS": "También puedes explorar temas de la comunidad más tarde en la configuración",
  "ldgKzl": "Error de autenticación durante el redireccionamiento de OAuth",
  "lfFsZ4": "Canales",
  "lglbRZ": "Volumen del usuario",
  "lhHlIR": "Actualmente estás en otra llamada. ¿Abandonarla y unirte a esta?",
  "lpIMne": "Las contraseñas no coinciden",
  "lqD5Zm": "Error al enviar el correo electrónico de verificación. Por favor, inténtalo de nuevo.",
  "lxQ+5m": "Asignado a",
  "lxentK": "Ocurrió un error inesperado",
  "lyuxFE": "Abandonar evento",
  "m0JQyS": "Procesando autorización",
  "m0jjCK": "Confidencial",
  "m16xKo": "Añadir",
  "m3DfE9": "¡Creado!",
  "m4itV1": "Error al guardar la personalización",
  "mFB2Q2": "No se encontraron reportes",
  "mFPcbZ": "Solicitud de amistad enviada a {0}",
  "mJUHUO": "(editado hace {mins}m)",
  "mJmlui": "Completa el perfil de tu bot con nombre, descripción y categorías",
  "mLacoq": "El nombre de usuario ya está en uso",
  "mT57+Q": "Ir a Ajustes",
  "mU/C6T": "Información del desarrollador",
  "mVyYg+": "Redirigiendo a autorización...",
  "mZGPxt": "Enlace de invitación copiado al portapapeles",
  "meAa31": "Aún no hay conversaciones",
  "mfXdhF": "El enlace de restablecimiento ha expirado. Por favor, solicita uno nuevo.",
  "mgkoHE": "Eliminar mensaje",
  "miO4ii": "Error al cargar los reportes",
  "mjkHcT": "malas, palabras, aquí",
  "mm9fVj": "Por favor, introduce un código válido de 6 dígitos",
  "moO8pM": "El usuario ha sido desbaneado",
  "mrOcNE": "No tienes permiso para enviar mensajes en este canal",
  "mskkA9": "Mover a la barra lateral",
  "muObp0": "Cualquiera puede enviarte un mensaje directo, incluso si no comparten un servidor.",
  "mxzaQk": "Privilegios de administrador eliminados con éxito",
  "n0b8L3": "Bots activos",
  "n1XEon": "Autorización fallida",
  "n1ekoW": "Iniciar sesión",
  "n2aBCc": "No se encontraron servidores",
  "n2nMp7": "Sesión cerrada con éxito",
  "n39nZ6": "Rol de sistema",
  "n5NZhM": "Todos los amigos — {0}",
  "n9yU9X": "Vista previa en vivo",
  "nEUrSn": "Sin descripción disponible",
  "nEnsT5": "No se pudo determinar la hora del mensaje",
  "nHADWh": "🛡️ Administrador",
  "nHorhB": "Error al crear la categoría: {0}",
  "nHxJ8K": "Inicia sesión para autorizar una aplicación de terceros",
  "nKNtU/": "Mensajes directos de miembros del servidor deshabilitados",
  "nL+HHD": "Error al cargar la imagen",
  "nLrBgA": "Icono de la categoría",
  "nOPbWJ": "Derecha",
  "nOhz3x": "Cerrar sesión",
  "nSqogE": "Amigos en común",
  "nTWWCZ": "Baja",
  "nTXLMh": "Video de YouTube",
  "nWMRxa": "Desfijar",
  "nbVpF9": "Introduce la descripción del canal",
  "ngI+uk": "Canales exentos",
  "nkzIir": "Restablecimiento de contraseña completado",
  "nlqeMq": "Silenciar por completo todas las notificaciones",
  "nmrqlN": "Nuevo enlace de invitación generado",
  "nrNHeD": "Configuración de excepciones de canal",
  "nwIZlo": "Las notificaciones están bloqueadas.",
  "nwtY4N": "Algo salió mal",
  "nxaDMK": "Compartiendo pantalla",
  "o2YbwW": "Enlace de invitación del servidor",
  "o4YSEw": "Perfil del bot y metadatos",
  "o6OQlp": "Editar canal",
  "oEtgpf": "Se ajusta según la red",
  "oGA1Eu": "No hay solicitudes pendientes",
  "oOi11l": "Desplazarse al final",
  "oQhhrZ": "Tipo de canal desconocido: {0}",
  "oRH6Dq": "canal",
  "oRyrN4": "Modo lento activo — espera {0}:{1} antes de enviar de nuevo",
  "oVFGMF": "Error al actualizar el correo electrónico. Por favor, inténtalo de nuevo.",
  "oXOSPE": "En línea",
  "oXrKEF": "Volver al servidor",
  "oY0evT": "Título del evento",
  "oi25rL": "Letra mayúscula",
  "oi3Wwm": "Abre la carpeta para<0/>arrastrar los servidores aquí",
  "ojKCLU": "Asignado",
  "okT/Qi": "• Las cuentas de bot no se pueden convertir fácilmente de vuelta a cuentas de usuario",
  "okT5K8": "Más servidores ({0})",
  "okbw/q": "Enlace de invitación",
  "onAh4a": "Error al cerrar sesión",
  "opHx0s": "Error al mover al miembro",
  "ovBPCi": "Predeterminado",
  "ovGRyZ": "Editar tarea",
  "owVAIQ": "Configuración de notificaciones del servidor",
  "p0FDsG": "Actualizar categoría",
  "p1Q2eb": "Tema enviado para revisión",
  "p2/GCq": "Confirmar contraseña",
  "p3LucZ": "10 segundos",
  "p83AHq": "Falta la información del canal. Por favor, cierra y vuelve a abrir el modal.",
  "p8TFSk": "Sesión cerrada en todos los dispositivos",
  "pDHcem": "Error al generar el enlace de invitación",
  "pFg+7w": "Actualizado:",
  "pLagDX": "Para usar tu bot:",
  "pQtwQU": "Autorización completa",
  "pR/c4i": "Reglas del servidor",
  "pSHrWb": "Solo las personas con una invitación pueden unirse",
  "pYPSbk": "Editar categoría",
  "pYuDdQ": "Tu cuenta está siendo revisada por nuestro equipo. Podrás acceder a la plataforma una vez que tu cuenta haya sido aprobada.",
  "pZGjTf": "Error al actualizar el perfil",
  "pfRh+M": "No se encontraron aplicaciones",
  "phHO4f": "Abriendo el panel de configuración del bot...",
  "pi1oME": "Enviar mensaje",
  "pvnfJD": "Oscuro",
  "pzM0fr": "Error al cargar los registros de automod",
  "q+FaXD": "Verificación fallida",
  "q3bQoZ": "Aún no hay mensajes fijados.",
  "q51Epg": "Evento no encontrado",
  "q5loub": "En línea ahora",
  "q9xapm": "Error al subir la imagen de avatar",
  "qBtYxp": "Debes iniciar sesión para confirmar asistencia",
  "qERl58": "Desactivar A2F",
  "qIy7HY": "Canal de voz/video",
  "qJF26y": "Arrastra los servidores aquí para ocultar",
  "qJb6G2": "Intentar de nuevo",
  "qUTRDE": "Los mensajes en estos canales evitarán automod",
  "qVkGWK": "Fijar",
  "qavm0B": "Dispositivos",
  "qgL3+G": "No se encontraron participantes",
  "qk9Ric": "¡Notificaciones habilitadas!",
  "ql/vFu": "Estás baneado de este servidor",
  "qlLBvf": "Añadir amigo",
  "qlRO2c": "Modo lento (segundos)",
  "qlnO8j": "Enviar enlace de restablecimiento",
  "qqLY+j": "Personalización",
  "qqnreA": "Subiendo {0} de {1} archivo{2}...",
  "qsEYm5": "Añadir emoji",
  "qtbRfT": "Hasta que yo lo active de nuevo",
  "qzFp5D": "Todas las categorías",
  "r+f6ba": "Configuración predeterminada para nuevos miembros",
  "r1N+pw": "3 horas",
  "r48dNv": "Añade amigos para empezar a chatear",
  "r5afQD": "Se requiere un desafío de autenticación. Por favor, inténtalo de nuevo.",
  "rBdrPc": "Has abandonado el evento",
  "rGt1HT": "Fin del registro de auditoría",
  "rHKON4": "Tema aplicado",
  "rIPYOg": "¿Recuerdas tu contraseña?",
  "rJJbvP": "Quitar silencio localmente",
  "rMfG6U": " está escribiendo",
  "rOdoS5": "Incluir audio del sistema",
  "rOsxLC": "Crear canal",
  "rSUKbE": "Gestionar roles del servidor",
  "rT2cV+": "Cámara",
  "rTaaN1": "Enviar para revisión",
  "rTiFFY": "Error al eliminar la conversación",
  "rWZBQd": "Elige una contraseña segura para mantener tu cuenta a salvo. Serás redirigido para iniciar sesión tras el restablecimiento.",
  "rWrgpM": "Inicia una conversación con un amigo de tu lista de amigos",
  "rXHHYU": "Mensaje bloqueado",
  "rXaf/O": "Eliminar administrador",
  "rdegfe": "Detección de spam",
  "rdnF/5": "Fija los mensajes importantes para que sean fáciles de encontrar más tarde.",
  "ri/7MV": "Sin fecha establecida",
  "rimT/D": "Todos los mensajes",
  "rj3LPO": "¡Inicio de sesión exitoso!",
  "rn6SBY": "Quitar silencio",
  "rpW7cP": "Voz conectada",
  "rrt39P": "Usa esta clave para autenticar tu bot con la API de Echoed",
  "rrwcB6": "Cliente eliminado con éxito",
  "rsmjAo": "Suprimir @everyone y @here",
  "rt0nOM": "¡Nueva clave API generada con éxito!",
  "rxaY+5": "No molestar",
  "rxuSRN": "Solo verificados",
  "s1S4Xy": "Ya eres miembro de este servidor",
  "s1clzx": "Error al enviar el mensaje de voz. Por favor, inténtalo de nuevo.",
  "s4Fps5": "{0} asistiendo",
  "s5DjPz": "Tema eliminado",
  "s8MJc8": "48 kHz (Alta calidad)",
  "sHy+Wn": "Error al cargar la información del servidor",
  "sHySAv": "Creador del evento",
  "sIQwbf": "Error al actualizar la preferencia",
  "sKUg/J": "Añadir una nueva tarea al tablero",
  "sLZWnB": "Protección máxima",
  "sQpDn6": "Salir de pantalla completa",
  "sRhb0p": "Eliminar aplicación OAuth2",
  "sRy8+6": "Mis paquetes de idioma",
  "sTHSqp": "Encuentra a tus amigos",
  "sZ3+Ey": "Borrar tema",
  "sZUsQi": "Introduce el título de la tarea...",
  "sdkLy8": "Error al banear usuario",
  "sfSBuD": "Administrador del servidor eliminado",
  "silO9A": "nombre de usuario",
  "spSgiK": "Estás silenciado en el servidor por un administrador",
  "sr0UJD": "Volver",
  "sr5lX3": "Unirse al evento",
  "sr8KGB": "Iniciar llamada",
  "ssSAVy": "Ocurrió un error durante el inicio de sesión.",
  "stQsyd": "Error al eliminar el servidor. Por favor, inténtalo de nuevo.",
  "t/YqKh": "Eliminar",
  "t12JSP": "Editar evento",
  "t3SyZa": "Suprimir menciones de roles",
  "t3cPan": "Eliminar tarea",
  "t490IT": "por {0}",
  "t6lAf6": "Seleccionar un usuario",
  "t7TeQU": "Mensajes",
  "t8dIOP": "Spam",
  "t9yxlZ": "Reportes",
  "tBmnPU": "Amigos",
  "tCyvAw": "Adjuntar un archivo",
  "tE3Djd": "El catálogo debe ser un objeto JSON con pares clave-valor de cadena",
  "tEAw/4": "• Las cuentas de bot tienen permisos y limitaciones diferentes",
  "tEoNh7": "Este evento no existe.",
  "tH6QZL": "¿Estás seguro de que quieres eliminar {0}? Esta acción no se puede deshacer.",
  "tH9htz": "Usuario bloqueado",
  "tR3Wxn": "Error al mover el canal: {0}",
  "tRrsxv": "Crea tu cuenta y entra al sótano. Donde ocurren las conversaciones reales, lejos del ruido.",
  "tTo02/": "Descubrimiento de bots",
  "tVSmFT": "Cargando más...",
  "tWfKc7": "Añade una descripción...",
  "tXkhj/": "Iniciar",
  "tbR8Xx": "Cuenta deshabilitada",
  "tcSGLx": "Cambiar estado",
  "tfDRzk": "Guardar",
  "tnHeOD": "Por favor, espera",
  "ttQTIX": "Error al cargar la configuración de notificaciones",
  "ttgAxV": "Canal de tareas (Próximamente)",
  "tuS5Jz": "Desbloquear",
  "tygjyd": "Actualizar detalles de la tarea",
  "u+hJUa": "Avatar de usuario",
  "u/sHm3": "Paquete de idioma eliminado",
  "uAQUqI": "Estado",
  "uAreMS": "Nota de resolución (opcional)",
  "uBniZO": "Límite de tamaño de archivo",
  "uBv9wB": "Añadir participante",
  "uCOy+5": "Todos los usuarios coincidentes ya son tus amigos o eres tú",
  "uCi1F+": "Error al aplicar el paquete de idioma",
  "uCtxk8": "Elimina tu mensaje",
  "uDHJEu": "He leído y acepto las reglas y los términos del servidor",
  "uG+X9C": "Invitar al bot al servidor",
  "uHjoeb": "{0} añadido como administrador del servidor",
  "uIUVJT": "Iniciando sesión como",
  "uJAKKh": "Sin descripción disponible.",
  "uJY9gC": "Ocurrió un error al bloquear al usuario",
  "uLWyRh": "Volumen del altavoz: {speakerVolume}%",
  "uM96Pv": "Recibe una notificación por cada mensaje enviado en este servidor",
  "uN355O": "Crear evento",
  "uNxfJk": "Página {currentPage} de {totalPages}",
  "uRG4cO": "Error al cargar la personalización del servidor",
  "uSMfoN": "Verificar",
  "uWi2Q+": "Barra lateral",
  "uWx+oX": "Los usuarios deben confirmar que son mayores de 18 para ver",
  "uaoy/c": "Ocurrió un error al desbloquear al usuario",
  "uc4bOi": "Unidos recientemente",
  "uk1nCp": "Redirigiendo en unos segundos...",
  "ul1Atu": "Convirtiendo...",
  "uoWAKI": "Encuentra o busca una conversación",
  "uqMxZC": "Generar clave API",
  "uvbWX4": "Encuentra o inicia una conversación",
  "uz0leT": "Estado:",
  "v0ItTA": "Cargando registros...",
  "v4473r": "Solo @menciones",
  "vC78gl": "Cualquiera puede encontrar y unirse a este servidor",
  "vERlcd": "Perfil",
  "vHVH3m": "Opacidad de la imagen: {0}",
  "vLyv1R": "Ocultar",
  "vROkQu": "tareas",
  "vSJd18": "Video",
  "vU2cdP": "Ir al servidor",
  "vUjrrO": "Llamadas de MD entrantes",
  "vVHzlA": "Aplicación cliente",
  "vXIe7J": "Idioma",
  "vcxMiY": "Únete a mi servidor en Echoed",
  "vfIVaT": "Las acciones realizadas en este servidor aparecerán aquí",
  "vlhaS+": "Alternar lista de miembros",
  "vmtMQ/": "Servidor silenciado",
  "vn18mP": "Elige un usuario de la lista para iniciar una conversación",
  "vp5vfW": "1 hora",
  "vpyFAf": "Error al editar el mensaje. Por favor, inténtalo de nuevo.",
  "vsTgiC": "({0} calificación{1})",
  "vuU+Ku": "Mostrando {0} miembro{1}",
  "vvGf1t": "No tienes permiso para conectarte a este canal de voz",
  "vwGkYB": "La contraseña debe tener al menos 8 caracteres",
  "w/bY7R": "Registros",
  "w1V9df": "El servidor ha deshabilitado @here.",
  "w4GrA7": "Baneado",
  "w5ehWr": "Usado en {0} servidor{1}",
  "w5wBGx": "Desfijar de la parte superior",
  "w81HAn": "Reportar mensaje",
  "w9ZSK2": "¡Solicitud de amistad enviada!",
  "wEOkfr": "Tu correo electrónico ha sido verificado. Redirigiendo a la aplicación...",
  "wEp8H9": "Error al actualizar el canal",
  "wJijgU": "Ubicación",
  "wThGrS": "Ajustes de la aplicación",
  "wYCVhl": "que duró unos segundos",
  "wZuczt": "alguien",
  "wjUAS6": "No tienes permiso para incrustar enlaces en este canal.",
  "wkFh5z": "Solicitud de autorización inválida",
  "wlQNTg": "Miembros",
  "wujV36": "Actualizar tema",
  "wy10Gm": "Se requiere verificación adicional.",
  "x5hldM": "Verificación A2F fallida",
  "x7kYg/": "Por favor, inicia sesión para ver y responder a esta invitación al evento.",
  "xBO+wH": "canales",
  "xDAtGP": "Mensaje",
  "xDo1TN": "Sin relleno. Sin ruido. Solo tú y tu grupo, donde se reúne tu círculo íntimo.",
  "xG9K5x": "Opcional: URL al panel de configuración de tu bot. Esto se usará como el enlace \"Configurar\" cuando los usuarios gestionen tu bot en sus servidores.",
  "xIfRuO": "Error al actualizar el mensaje fijado. Por favor, inténtalo de nuevo.",
  "xLFTwf": "Altavoces",
  "xRPn3U": "Introduce tu dirección de correo electrónico",
  "xS8DTK": "No tienes permiso para hablar en este canal de voz",
  "xTrui6": "¿Estás seguro de que quieres eliminar \"{clientName}\"? Esta acción no se puede deshacer.",
  "xWHwwQ": "Baneos",
  "xYqNT7": "Permisos permitidos",
  "xZalR1": "Debes iniciar sesión para unirte a un servidor",
  "xcf3X7": "Código de verificación",
  "xfXC7q": "Canales de texto",
  "xhjagk": "Revertir al valor predeterminado",
  "xiC6Ke": "Unirse a nueva llamada",
  "xjFX7a": "Haz clic para eliminar tu reacción {0}",
  "xlYhLW": "Confidencial (Lado del servidor)",
  "xnbxVc": "¡Perfil del bot actualizado con éxito!",
  "xoBFet": "Buscar miembros",
  "xoZZ7r": "Descripción de los permisos",
  "xtCiui": "El usuario ya es administrador",
  "xw1Cjb": "bot{0}",
  "xz/nFd": "Servidor actualizado con éxito",
  "y/0uwd": "Ayer",
  "y9GccI": "Personalización guardada con éxito",
  "yA0J7V": "Controla quién tiene permitido iniciar una conversación de mensaje directo contigo",
  "yDOdwQ": "Gestión de usuarios",
  "yFMpcv": "Historial de mensajes",
  "yIObNA": "Letra minúscula",
  "yIVrHZ": "Autorizar",
  "yNVhzm": "Introduce un nombre de usuario o nombre para buscar",
  "yQ2kGp": "Cargar más",
  "yQE2r9": "Cargando",
  "yRnk5W": "Clave API",
  "yTYVhB": "Se requiere el código de autenticador para desactivar la A2F",
  "ycd3i1": "Tú y {0} son amigos",
  "ygCKqB": "Detener",
  "ygGUsT": "Error al abandonar el servidor",
  "yhMze7": "Inicia tu comunidad",
  "yjkELF": "Confirmar nueva contraseña",
  "ymcaNq": "Suelta para actualizar",
  "yrmvkV": "{0} archivo(s) exceden el límite de 10MB por archivo",
  "yuZcMi": "Código de invitación inválido o expirado",
  "yulICV": "al grupo.",
  "ywFj2D": "Configuración",
  "ywHFeZ": "Llamaste a {recipientName} (sin respuesta)",
  "ywXnPs": "El bot no tiene un panel de configuración",
  "yx/fMc": "Alta",
  "yz7wBu": "Cerrar",
  "z1478T": "Aviso de seguridad",
  "zEoDmM": "Configura la moderación automática para <0>{0}</0>",
  "zF+Pew": "Toca el icono del menú <0/>",
  "zFT5rr": "completado",
  "zH/U2J": "Grabando...",
  "zLinIo": "El nombre de usuario está disponible",
  "zN+3Av": "Anuncios, para siempre",
  "zQIolL": "¿Qué sigue?",
  "zQNDqP": "Borrar tema",
  "zWsPjy": "Permitir que los miembros de este servidor te envíen mensajes directos",
  "zaiGW8": "Ocurrió un error en la llamada",
  "zjNBEU": "Descubre y autoriza aplicaciones de terceros para tu cuenta de Echoed",
  "zoJoev": "No hay roles personalizados",
  "zp4X78": "No hay canales en esta categoría",
  "zpT65N": "Calidad adaptativa",
  "zqQ1Xw": "Describe tu servidor (opcional)",
  "zrTBgJ": "Coincidió:",
  "zsJUbn": "Más antiguos",
  "zsslJv": "Sin contenido",
  "zt9iD/": "Cuenta pendiente de revisión",
  "ztGxi6": "Rechazada",
  "zuoIYL": "Altavoz",
  "zvWmGz": "¿OLVIDASTE TU",
  "zwBp5t": "Privado",
  "zwCqGB": "Qué hacer cuando se activa una regla",
  "zx4BuL": "Semana",
  "zxe/C/": "Volumen del altavoz",
  "zyHhY3": "ID de cliente copiado al portapapeles"
}
